withorbit_sdk/__init__.py
withorbit_sdk/client.py
withorbit_sdk/types.py
withorbit_sdk/wrappers/__init__.py
withorbit_sdk/wrappers/anthropic.py
withorbit_sdk/wrappers/google.py
withorbit_sdk/wrappers/openai.py
withorbit_sdk-0.1.4.dist-info/METADATA
withorbit_sdk-0.1.4.dist-info/WHEEL
withorbit_sdk-0.1.4.dist-info/top_level.txt
withorbit_sdk-0.1.4.dist-info/RECORD
